AUTHORS
HISTORY
LICENSE
MANIFEST.in
README.rst
setup.cfg
setup.py
django_twostepauth.egg-info/PKG-INFO
django_twostepauth.egg-info/SOURCES.txt
django_twostepauth.egg-info/dependency_links.txt
django_twostepauth.egg-info/entry_points.txt
django_twostepauth.egg-info/not-zip-safe
django_twostepauth.egg-info/requires.txt
django_twostepauth.egg-info/top_level.txt
docs/index.rst
docs/install.rst
exampleapp/demoapp/__init__.py
exampleapp/demoapp/models.py
exampleapp/demoapp/signals.py
twostepauth/__init__.py
twostepauth/admin.py
twostepauth/auth_backend.py
twostepauth/forms.py
twostepauth/models.py
twostepauth/settings.py
twostepauth/utils.py
twostepauth/views.py
twostepauth/fixtures/test_users.json
twostepauth/management/__init__.py
twostepauth/management/commands/__init__.py
twostepauth/management/commands/generate_twostepauth_secret.py
twostepauth/templates/twostepauth/adminlogin.html
twostepauth/templates/twostepauth/login.html
twostepauth/templates/twostepauth/signin_token_form.html
twostepauth/tests/__init__.py
twostepauth/tests/auth_backend.py
twostepauth/tests/base.py
twostepauth/tests/forms.py
twostepauth/tests/urls.py
twostepauth/tests/utils.py
twostepauth/tests/views.py
twostepauth/tests/templates/base.html
twostepauth/tests/templates/twostepauth/profile.html