Metadata-Version: 1.0
Name: django-twostepauth
Version: 0.1dev
Summary: Two-step authentication for Django
Home-page: https://bitbucket.org/cogni/django-twostepauth
Author: Nuno Maltez, Pedro Lima
Author-email: nuno@cognitiva.com, pedro@cognitiva.com
License: BSD
Keywords: django,authentication
Platform: OS Independent
Classifier: Development Status :: 4 - Beta
Classifier: Intended Audience :: Developers
Classifier: Framework :: Django
Classifier: License :: OSI Approved :: BSD License
Classifier: Operating System :: OS Independent
Classifier: Programming Language :: Python
Classifier: Topic :: Internet :: WWW/HTTP
